era5/__init__.py
era5/downloader.py
era5/validator.py
data_download-0.1.0.dist-info/LICENSE
data_download-0.1.0.dist-info/METADATA
data_download-0.1.0.dist-info/WHEEL
data_download-0.1.0.dist-info/top_level.txt
data_download-0.1.0.dist-info/RECORD
