Metadata-Version: 2.1
Name: data-download
Version: 0.1.0
Summary: Download ERA5 data from Copernicus API
Home-page: https://github.com/himpactlab/Data_download
Author: Sididk Barbhuiya
Author-email: siddikbarbhuiya@gmail.com
Classifier: Programming Language :: Python :: 3
Classifier: License :: OSI Approved :: MIT License
Classifier: Operating System :: OS Independent
Requires-Python: >=3.6
License-File: LICENSE
Requires-Dist: cdsapi
Requires-Dist: xarray
Requires-Dist: netCDF4
